api_blueprint_generator/__init__.py
api_blueprint_generator/cli.py
api_blueprint_generator/parser.py
api_blueprint_generator/utils.py
api_blueprint_generator/validation.py
api_blueprint_generator/generators/__init__.py
api_blueprint_generator/generators/base_generator.py
api_blueprint_generator/generators/fastapi_generator.py
api_blueprint_generator/generators/flask_generator.py
"api_blueprint_generator/templates/alembic/env.py,j2"
api_blueprint_generator/templates/fastapi/.env.j2
api_blueprint_generator/templates/fastapi/.env.py.j2
api_blueprint_generator/templates/fastapi/Dockerfile.j2
api_blueprint_generator/templates/fastapi/README.md.j2
api_blueprint_generator/templates/fastapi/alembic.ini.j2
api_blueprint_generator/templates/fastapi/auth.py.j2
api_blueprint_generator/templates/fastapi/auth_routes.py.j2
api_blueprint_generator/templates/fastapi/conftest.py.j2
api_blueprint_generator/templates/fastapi/crud.py.j2
api_blueprint_generator/templates/fastapi/database.py.j2
api_blueprint_generator/templates/fastapi/dependencies.py.j2
api_blueprint_generator/templates/fastapi/docker-compose.yml.j2
api_blueprint_generator/templates/fastapi/docker-entrypoint.sh.j2
api_blueprint_generator/templates/fastapi/main.py.j2
api_blueprint_generator/templates/fastapi/model_routes.py.j2
api_blueprint_generator/templates/fastapi/models.py.j2
api_blueprint_generator/templates/fastapi/router.py.j2
api_blueprint_generator/templates/fastapi/schemas.py.j2
api_blueprint_generator/templates/fastapi/app/config.py.j2
api_blueprint_generator/templates/fastapi/app/tasks.py.j2
api_blueprint_generator/templates/fastapi/app/worker.py.j2
api_blueprint_generator/templates/fastapi/tests/conftest.py.j2
api_blueprint_generator/templates/fastapi/tests/test_auth.py.j2
api_blueprint_generator/templates/fastapi/tests/test_model_crud.py.j2
api_blueprint_generator/templates/flask/models.py.j2
api_blueprint_generator-1.0.0.dist-info/licenses/LICENSE
app/__init__.py
app/auth.py
app/crud.py
app/database.py
app/main.py
app/models.py
app/schemas.py
api_blueprint_generator-1.0.0.dist-info/METADATA
api_blueprint_generator-1.0.0.dist-info/WHEEL
api_blueprint_generator-1.0.0.dist-info/entry_points.txt
api_blueprint_generator-1.0.0.dist-info/top_level.txt
api_blueprint_generator-1.0.0.dist-info/RECORD
