Metadata-Version: 2.4
Name: api-blueprint-generator
Version: 1.0.0
Summary: Generate production-ready APIs from a simple Markdown specification.
Home-page: https://github.com/your_username/Project-API-Blueprint-Strategy
Author: James The Giblet
Author-email: your_email@example.com
Classifier: Programming Language :: Python :: 3
Classifier: Programming Language :: Python :: 3.11
Classifier: License :: OSI Approved :: MIT License
Classifier: Operating System :: OS Independent
Classifier: Development Status :: 5 - Production/Stable
Classifier: Intended Audience :: Developers
Classifier: Topic :: Software Development :: Code Generators
Classifier: Topic :: Software Development :: Build Tools
Classifier: Framework :: FastAPI
Classifier: Typing :: Typed
Requires-Python: >=3.8
License-File: LICENSE
Requires-Dist: click>=8.0
Requires-Dist: jinja2>=3.0
Requires-Dist: pyyaml>=6.0
Requires-Dist: python-frontmatter>=1.0
Dynamic: author
Dynamic: author-email
Dynamic: classifier
Dynamic: description
Dynamic: description-content-type
Dynamic: home-page
Dynamic: license-file
Dynamic: requires-dist
Dynamic: requires-python
Dynamic: summary
